{"type":"FeatureCollection","features":[{"type":"Feature","properties":{"organizationName":"University of Southern California","studentPopulation":52376,"yearFounded":1880,"RoundedunderGraduatePercentage":0.4},"geometry":{"type":"Point","coordinates":[-118.282761,34.019231]}},{"type":"Feature","properties":{"organizationName":"University of California, Los Angeles","studentPopulation":46947,"yearFounded":1919,"RoundedunderGraduatePercentage":0.7},"geometry":{"type":"Point","coordinates":[-118.437855,34.073903]}},{"type":"Feature","properties":{"organizationName":"California State University, Long Beach","studentPopulation":42378,"yearFounded":1949,"RoundedunderGraduatePercentage":0.8,"marker-color":"#c8a809","marker-size":"medium"},"geometry":{"type":"Point","coordinates":[-118.122401,33.782235]}},{"type":"Feature","properties":{"organizationName":"California State University, Northridge","studentPopulation":42736,"yearFounded":1958,"RoundedunderGraduatePercentage":0.9,"marker-color":"#00bd52","marker-size":"medium"},"geometry":{"type":"Point","coordinates":[-118.52864,34.235511]}},{"type":"Feature","properties":{"organizationName":"California State University, Fullerton","studentPopulation":46245,"yearFounded":1957,"RoundedunderGraduatePercentage":0.9,"marker-color":"#fe8686","marker-size":"medium"},"geometry":{"type":"Point","coordinates":[-117.929104,33.870325]}}]}